{"updated":"2021-05-13 13:09:08","zentai":[{"id":"tag:qiita.com,2005:PublicArticle/1433745","published":"2021-05-11T19:16:56Z","updated":"2021-05-11T19:17:52Z","link":"https://qiita.com/shoito66/items/5eb1b558fdd972e4be2b","url":"https://qiita.com/shoito66/items/5eb1b558fdd972e4be2b","title":"プログラミング初心者向け！トイドローン「Tello」をScratchで飛ばす","author":"shoito66"},{"id":"tag:qiita.com,2005:PublicArticle/1433053","published":"2021-05-10T00:21:00Z","updated":"2021-05-10T18:28:57Z","link":"https://qiita.com/watamino/items/ad516a1b33a175af459b","url":"https://qiita.com/watamino/items/ad516a1b33a175af459b","title":"毎朝時間がなくて星占いチェックができないなら、自分で作ってみよう！と「今日の運勢占いBot」を作ってみた！","author":"watamino"},{"id":"tag:qiita.com,2005:PublicArticle/1432913","published":"2021-05-09T19:47:04Z","updated":"2021-05-09T19:47:04Z","link":"https://qiita.com/kkyosuke17/items/2f060ca2ecf4c7505281","url":"https://qiita.com/kkyosuke17/items/2f060ca2ecf4c7505281","title":"迷えるあなたに意思決定LINEBot！エヴァのMAGIが判断してくれます！","author":"kkyosuke17"},{"id":"tag:qiita.com,2005:PublicArticle/1432906","published":"2021-05-09T19:32:04Z","updated":"2021-05-09T19:32:04Z","link":"https://qiita.com/n0bisuke/items/48bfac5a935c69c3b1e4","url":"https://qiita.com/n0bisuke/items/48bfac5a935c69c3b1e4","title":"Cloud Foundryのデプロイで急にNode.jsが動かなくなった件","author":"n0bisuke"},{"id":"tag:qiita.com,2005:PublicArticle/1432815","published":"2021-05-09T16:02:00Z","updated":"2021-05-10T12:36:59Z","link":"https://qiita.com/kokano23/items/b34b7d0361b8aaa6ad1f","url":"https://qiita.com/kokano23/items/b34b7d0361b8aaa6ad1f","title":"「ひらがな化API」を使って、給食メニュー変換Botを作ったら、わが子に大好評だった話","author":"kokano23"},{"id":"tag:qiita.com,2005:PublicArticle/1432807","published":"2021-05-09T15:47:45Z","updated":"2021-05-09T15:47:45Z","link":"https://qiita.com/shoito66/items/d0a411223d0b7f8c30de","url":"https://qiita.com/shoito66/items/d0a411223d0b7f8c30de","title":"Google Cloud Vision APIを使って画像認識してくれるLINE Botを作る","author":"shoito66"},{"id":"tag:qiita.com,2005:PublicArticle/1432768","published":"2021-05-09T14:29:46Z","updated":"2021-05-09T14:29:46Z","link":"https://qiita.com/ShinsukeSutou/items/2b40c7ed5a2475b73cdc","url":"https://qiita.com/ShinsukeSutou/items/2b40c7ed5a2475b73cdc","title":"タイトルを呟いたらポスターとあらすじを答える映画どろbotを作ってみた ","author":"ShinsukeSutou"},{"id":"tag:qiita.com,2005:PublicArticle/1432453","published":"2021-05-08T20:10:48Z","updated":"2021-05-12T18:46:22Z","link":"https://qiita.com/ranchi1977/items/fff2dc52def04f6a8cee","url":"https://qiita.com/ranchi1977/items/fff2dc52def04f6a8cee","title":"API初心者向け「さけのわAPIで日本酒お勧めLINEボット」を作って苦戦した、APIレスポンスの処理解説","author":"ranchi1977"},{"id":"tag:qiita.com,2005:PublicArticle/1431955","published":"2021-05-07T21:42:50Z","updated":"2021-05-09T08:26:40Z","link":"https://qiita.com/suo-takefumi/items/2bbcc3fd9af02acbeb26","url":"https://qiita.com/suo-takefumi/items/2bbcc3fd9af02acbeb26","title":"[AWS][boto3][create_stack] CloudFormationスタックをシリアルに実行するサンプルスクリプト","author":"suo-takefumi"},{"id":"tag:qiita.com,2005:PublicArticle/1431693","published":"2021-05-07T11:30:37Z","updated":"2021-05-08T11:21:16Z","link":"https://qiita.com/cog1t0/items/c935495955fb7ca4220a","url":"https://qiita.com/cog1t0/items/c935495955fb7ca4220a","title":"RailsでCSV出力をviewに任せる実装","author":"cog1t0"},{"id":"tag:qiita.com,2005:PublicArticle/1431449","published":"2021-05-06T19:35:55Z","updated":"2021-05-06T19:35:55Z","link":"https://qiita.com/tkyko13/items/2ac5639800c73fe89fe8","url":"https://qiita.com/tkyko13/items/2ac5639800c73fe89fe8","title":"Nuxtjs × Netlify Functionsを始める際のメモ","author":"tkyko13"},{"id":"tag:qiita.com,2005:PublicArticle/1430426","published":"2021-05-04T17:43:15Z","updated":"2021-05-04T17:43:15Z","link":"https://qiita.com/n0bisuke/items/832e465bfe61d98a1d65","url":"https://qiita.com/n0bisuke/items/832e465bfe61d98a1d65","title":"GitHub ActionsでCloud Foundry（IBM Cloud）のデプロイを行う","author":"n0bisuke"},{"id":"tag:qiita.com,2005:PublicArticle/1430422","published":"2021-05-04T17:37:11Z","updated":"2021-05-04T17:37:11Z","link":"https://qiita.com/n0bisuke/items/fcaf38b26f84dc6898d3","url":"https://qiita.com/n0bisuke/items/fcaf38b26f84dc6898d3","title":"GitHub Actionsのログをマスクするメモ","author":"n0bisuke"},{"id":"tag:qiita.com,2005:PublicArticle/1430269","published":"2021-05-04T12:14:54Z","updated":"2021-05-04T12:14:54Z","link":"https://qiita.com/n0bisuke/items/59f860fa4759978506a6","url":"https://qiita.com/n0bisuke/items/59f860fa4759978506a6","title":"Cloud Foundry（IBM Cloud）で環境変数を使うメモ","author":"n0bisuke"},{"id":"tag:qiita.com,2005:PublicArticle/1430260","published":"2021-05-04T11:58:52Z","updated":"2021-05-04T12:00:43Z","link":"https://qiita.com/n0bisuke/items/8fc4d2c1b032e1c35206","url":"https://qiita.com/n0bisuke/items/8fc4d2c1b032e1c35206","title":"Cloud Foundry（IBM Cloud）でNode.jsのバージョン指定【.nvmrc】","author":"n0bisuke"},{"id":"tag:qiita.com,2005:PublicArticle/1430250","published":"2021-05-04T11:42:54Z","updated":"2021-05-04T11:42:54Z","link":"https://qiita.com/n0bisuke/items/d61912cccfac21447650","url":"https://qiita.com/n0bisuke/items/d61912cccfac21447650","title":"Cloud Foundry（IBM Cloud）にDiscord BOTをデプロイしようとした際にハマったメモ","author":"n0bisuke"},{"id":"tag:qiita.com,2005:PublicArticle/1430129","published":"2021-05-04T00:39:26Z","updated":"2021-05-05T10:43:55Z","link":"https://qiita.com/n0bisuke/items/47ee043fc6cf1b5168c2","url":"https://qiita.com/n0bisuke/items/47ee043fc6cf1b5168c2","title":"Node.jsでGoogle Spread Sheetsを読み取る 【Sheet API v4】","author":"n0bisuke"},{"id":"tag:qiita.com,2005:PublicArticle/1429980","published":"2021-05-03T18:59:07Z","updated":"2021-05-03T18:59:24Z","link":"https://qiita.com/n0bisuke/items/ba3ed0a43642a966f635","url":"https://qiita.com/n0bisuke/items/ba3ed0a43642a966f635","title":"Discord BOTを特定チャンネルで呼びかけると反応するようにするメモ","author":"n0bisuke"},{"id":"tag:qiita.com,2005:PublicArticle/1429862","published":"2021-05-03T15:18:45Z","updated":"2021-05-03T15:44:04Z","link":"https://qiita.com/n0bisuke/items/93d30b863380df59163b","url":"https://qiita.com/n0bisuke/items/93d30b863380df59163b","title":"ローカルのgitのデフォルトブランチをmainにしておくメモ","author":"n0bisuke"},{"id":"tag:qiita.com,2005:PublicArticle/1429843","published":"2021-05-03T14:48:00Z","updated":"2021-05-03T21:40:14Z","link":"https://qiita.com/grayhamchan/items/79021a37504845535643","url":"https://qiita.com/grayhamchan/items/79021a37504845535643","title":"ちょっとしたアニメーションGIFならパワーポイントで作成できる","author":"grayhamchan"}]}